magicidentify/__init__.py
magicidentify/tools/__init__.py
magicidentify/tools/magicidentifycli.py
magic_identify-0.2.2.dist-info/LICENSE
magic_identify-0.2.2.dist-info/METADATA
magic_identify-0.2.2.dist-info/WHEEL
magic_identify-0.2.2.dist-info/entry_points.txt
magic_identify-0.2.2.dist-info/top_level.txt
magic_identify-0.2.2.dist-info/RECORD
