Metadata-Version: 2.1
Name: magic-identify
Version: 0.2.2
Summary: A python module and command to try really hard to get a mime-type for a file
Home-page: https://github.com/hardaker/magic-identify
Author: Wes Hardaker
Author-email: opensource@hardakers.net
License: UNKNOWN
Platform: UNKNOWN
Classifier: Programming Language :: Python :: 3
Classifier: Operating System :: OS Independent
Requires-Python: >=3.6
License-File: LICENSE
Requires-Dist: python-magic (>=0.4.24)
Requires-Dist: identify (>=2.2.13)
